uxu/__about__.py
uxu/__init__.py
uxu/element.py
uxu/fiber.py
uxu/html.py
uxu/listdiff.py
uxu/manager.py
uxu/patch.py
uxu/persistence.py
uxu/proxy_reactor.py
uxu/rendering.py
uxu/serve.py
uxu/session.py
uxu/textnode.py
uxu/util.py
uxu/vdom.py
uxu/lsp/README.md
uxu/lsp/__init__.py
uxu/lsp/server.py
uxu/lsp/types.py
uxu/rpc/__init__.py
uxu/rpc/io_transport.py
uxu/rpc/jsonrpc.py
uxu/rpc/starlette_ws_transport.py
uxu/rpc/transport.py
uxu/rpc/websocket_transport.py
uxu-0.1.1.dist-info/METADATA
uxu-0.1.1.dist-info/WHEEL
uxu-0.1.1.dist-info/licenses/LICENSE.txt
uxu-0.1.1.dist-info/RECORD
