Metadata-Version: 2.1
Name: uxu
Version: 0.1.1
Summary: Server-side interactive HTML engine.
Project-URL: Documentation, https://github.com/EdAyers/sss/uxu
Project-URL: Issues, https://github.com/EdAyers/sss/issues
Project-URL: Source, https://github.com/EdAyers/sss/uxu
Author-email: "E.W.Ayers" <contact@edayers.com>
License-Expression: MIT
License-File: LICENSE.txt
Classifier: Development Status :: 4 - Beta
Classifier: Programming Language :: Python
Classifier: Programming Language :: Python :: 3.9
Classifier: Programming Language :: Python :: 3.10
Classifier: Programming Language :: Python :: 3.11
Classifier: Programming Language :: Python :: Implementation :: CPython
Classifier: Programming Language :: Python :: Implementation :: PyPy
Requires-Python: >=3.9
Requires-Dist: dominate
Requires-Dist: html5lib
Requires-Dist: miniscutil
Requires-Dist: pydantic
Requires-Dist: pydantic[dotenv]
Requires-Dist: python-jose
Requires-Dist: starlette
Requires-Dist: websockets
